fodpy/__init__.py
fodpy-0.0.1.dist-info/LICENSE
fodpy-0.0.1.dist-info/METADATA
fodpy-0.0.1.dist-info/WHEEL
fodpy-0.0.1.dist-info/top_level.txt
fodpy-0.0.1.dist-info/RECORD
