Metadata-Version: 2.1
Name: fodpy
Version: 0.0.1
Summary: fod provides some tools for fiber orientation distribution at the voxel level
Home-page: https://github.com/vic-dragon/BJS
Author: Seungyong Hwang
Author-email: hsy0264@gmail.com
License: UNKNOWN
Platform: UNKNOWN
Classifier: Programming Language :: Python :: 3
Classifier: License :: OSI Approved :: GNU General Public License v3 (GPLv3)
Classifier: Operating System :: OS Independent
Requires-Python: >=3.6
